MANIFEST.in
README.rst
setup.py
docs/HISTORY.rst
pd/__init__.py
pd.contentrules.sms.egg-info/PKG-INFO
pd.contentrules.sms.egg-info/SOURCES.txt
pd.contentrules.sms.egg-info/dependency_links.txt
pd.contentrules.sms.egg-info/entry_points.txt
pd.contentrules.sms.egg-info/namespace_packages.txt
pd.contentrules.sms.egg-info/not-zip-safe
pd.contentrules.sms.egg-info/requires.txt
pd.contentrules.sms.egg-info/top_level.txt
pd/contentrules/__init__.py
pd/contentrules/sms/__init__.py
pd/contentrules/sms/configure.zcml
pd/contentrules/sms/i18n.sh
pd/contentrules/sms/actions/__init__.py
pd/contentrules/sms/actions/configure.zcml
pd/contentrules/sms/actions/sms.py
pd/contentrules/sms/locales/pd.contentrules.sms-manual.pot
pd/contentrules/sms/locales/pd.contentrules.sms.pot
pd/contentrules/sms/locales/rebuildAll.sh
pd/contentrules/sms/locales/it/LC_MESSAGES/pd.contentrules.sms.po
pd/contentrules/sms/tests/__init__.py